{
    "tower": {
        "url": "static/image/信号塔.png",
        "width": "38",
        "height": "37"
    },
    "00": {
        "url": "static/image/军舰.png",
        "width": "129",
        "height": "42"
    },
    "01": {
        "url": "static/image/数据链.png",
        "width": "86",
        "height": "60"
    },
    "02": {
        "url": "static/image/船1.png",
        "width": "79",
        "height": "22"
    },
    "03": {
        "url": "static/image/船2.png",
        "width": "89",
        "height": "23"
    },
    "04": {
        "url": "static/image/直升机.png",
        "width": "83",
        "height": "32"
    },
    "05": {
        "url": "static/image/塔康.png",
        "width": "156",
        "height": "106"
    }
}